pygame_visor/__init__.py
pygame_visor/py.typed
pygame_visor/types.py
pygame_visor/video.py
pygame_visor/visor.py
pygame_visor-0.4.1.dist-info/licenses/LICENSE
pygame_visor-0.4.1.dist-info/WHEEL
pygame_visor-0.4.1.dist-info/METADATA
pygame_visor-0.4.1.dist-info/RECORD
