Metadata-Version: 2.4
Name: pygame-visor
Version: 0.4.1
Summary: Pygame Visor - a simple Camera/Viewport library
Author: Nitori
Author-email: Nitori <nitori@chireiden.net>
License-Expression: MIT
License-File: LICENSE
Requires-Python: >=3.12
